pta/PixivTagAnalyzer.py
pta/__init__.py
pta/main.py
pta/py.typed
pixiv_tag_analyzer-1.6.0.dist-info/LICENSE
pixiv_tag_analyzer-1.6.0.dist-info/METADATA
pixiv_tag_analyzer-1.6.0.dist-info/WHEEL
pixiv_tag_analyzer-1.6.0.dist-info/entry_points.txt
pixiv_tag_analyzer-1.6.0.dist-info/top_level.txt
pixiv_tag_analyzer-1.6.0.dist-info/RECORD
